zanthor/__init__.py
zanthor/__main__.py
zanthor/_effects.py
zanthor/algo.py
zanthor/cannon.py
zanthor/castle.py
zanthor/const.py
zanthor/cyclic_list.py
zanthor/effect.py
zanthor/explode.py
zanthor/factory.py
zanthor/fire.py
zanthor/flock.py
zanthor/html.py
zanthor/human.py
zanthor/interface.py
zanthor/intro.py
zanthor/isovid.py
zanthor/items.py
zanthor/level.py
zanthor/main.py
zanthor/menu.py
zanthor/messages.py
zanthor/robot.py
zanthor/sound_info.py
zanthor/sounds.py
zanthor/states.py
zanthor/steam.py
zanthor/tiles.py
zanthor/title.py
zanthor/truck.py
zanthor/units.py
zanthor/util.py
zanthor/data/gfx/background_bottom.png
zanthor/data/gfx/background_equipment.png
zanthor/data/gfx/background_illustration.png
zanthor/data/gfx/background_status_left.png
zanthor/data/gfx/caastles.png
zanthor/data/gfx/castle1.png
zanthor/data/gfx/castle1.tga
zanthor/data/gfx/coal.png
zanthor/data/gfx/hairs.png
zanthor/data/gfx/hairs.tga
zanthor/data/gfx/heart.png
zanthor/data/gfx/heart.xcf.bz2
zanthor/data/gfx/heart_pulse.png
zanthor/data/gfx/hole.png
zanthor/data/gfx/hole2.png
zanthor/data/gfx/hole3.png
zanthor/data/gfx/hole4.png
zanthor/data/gfx/tileedit.ini
zanthor/data/gfx/tileedit.py
zanthor/data/gfx/tiles.png
zanthor/data/gfx/tiles.tga
zanthor/data/gfx/tiles2.png
zanthor/data/gfx/tiles2.tga
zanthor/data/intro/ETHNOCEN.TTF
zanthor/data/intro/WALSHES.TTF
zanthor/data/intro/dazzlesh.ttf
zanthor/data/intro/grass.ogg
zanthor/data/intro/intro1.ogg
zanthor/data/intro/introbg.png
zanthor/data/intro/mybkgr.png
zanthor/data/intro/read_me.html
zanthor/data/intro/soundtrack1.ogg
zanthor/data/intro/soundtrack2.ogg
zanthor/data/intro/soundtrack3.ogg
zanthor/data/intro/title.jpg
zanthor/data/intro/zanthor.ogg
zanthor/data/levels/codes.tga
zanthor/data/levels/level1.png
zanthor/data/levels/level1.tga
zanthor/data/levels/level2.png
zanthor/data/levels/level2.tga
zanthor/data/levels/level3.tga
zanthor/data/levels/level4.tga
zanthor/data/levels/level5.tga
zanthor/data/levels/level6.tga
zanthor-1.2.4.dist-info/LICENSE.txt
zanthor-1.2.4.dist-info/METADATA
zanthor-1.2.4.dist-info/WHEEL
zanthor-1.2.4.dist-info/entry_points.txt
zanthor-1.2.4.dist-info/top_level.txt
zanthor-1.2.4.dist-info/RECORD
