Metadata-Version: 2.1
Name: zanthor
Version: 1.2.4
Summary: Zanthor is a game where you play an evil robot castle which is powered by steam.  @zanthorgame #python #pygame
Home-page: http://github.com/pygame/zanthor/
Author: Aaron, Phil, Rene, Tim
Author-email: renesd@gmail.com
Maintainer: Rene Dudfield
Maintainer-email: renesd@gmail.com
License: GPL
Classifier: Development Status :: 4 - Beta
Classifier: License :: OSI Approved :: GNU Lesser General Public License v2 or later (LGPLv2+)
Classifier: Programming Language :: Python :: 2
Classifier: Programming Language :: Python :: 2.7
Classifier: Programming Language :: Python :: 3
Classifier: Programming Language :: Python :: 3.0
Classifier: Programming Language :: Python :: 3.1
Classifier: Programming Language :: Python :: 3.2
Classifier: Programming Language :: Python :: 3.3
Classifier: Programming Language :: Python :: 3.4
Classifier: Programming Language :: Python :: 3.5
Classifier: Programming Language :: Python :: 3.6
Classifier: Programming Language :: Python :: 3.7
Classifier: Programming Language :: Python :: 3.8
Classifier: Programming Language :: Python :: 3.9
Classifier: Programming Language :: Python :: 3.10
Classifier: Programming Language :: Python :: 3.11
Classifier: Programming Language :: Python :: 3.12
Classifier: Topic :: Software Development :: Libraries :: pygame
Classifier: Topic :: Games/Entertainment :: Arcade
Classifier: Topic :: Games/Entertainment :: Real Time Strategy
License-File: LICENSE.txt
Requires-Dist: pygame
